odoo/addons/account_cutoff_accrual_subscription/README.rst
odoo/addons/account_cutoff_accrual_subscription/__init__.py
odoo/addons/account_cutoff_accrual_subscription/__manifest__.py
odoo/addons/account_cutoff_accrual_subscription/i18n/account_cutoff_accrual_subscription.pot
odoo/addons/account_cutoff_accrual_subscription/i18n/es.po
odoo/addons/account_cutoff_accrual_subscription/i18n/fr.po
odoo/addons/account_cutoff_accrual_subscription/i18n/it.po
odoo/addons/account_cutoff_accrual_subscription/models/__init__.py
odoo/addons/account_cutoff_accrual_subscription/models/account_cutoff.py
odoo/addons/account_cutoff_accrual_subscription/models/account_cutoff_accrual_subscription.py
odoo/addons/account_cutoff_accrual_subscription/models/account_cutoff_line.py
odoo/addons/account_cutoff_accrual_subscription/readme/CONFIGURE.md
odoo/addons/account_cutoff_accrual_subscription/readme/CONTRIBUTORS.md
odoo/addons/account_cutoff_accrual_subscription/readme/DESCRIPTION.md
odoo/addons/account_cutoff_accrual_subscription/security/ir.model.access.csv
odoo/addons/account_cutoff_accrual_subscription/security/ir_rule.xml
odoo/addons/account_cutoff_accrual_subscription/static/description/icon.png
odoo/addons/account_cutoff_accrual_subscription/static/description/index.html
odoo/addons/account_cutoff_accrual_subscription/views/account_cutoff_accrual_subscription.xml
odoo/addons/account_cutoff_accrual_subscription/views/account_cutoff_line.xml
odoo_addon_account_cutoff_accrual_subscription-18.0.1.0.0.3.dist-info/METADATA
odoo_addon_account_cutoff_accrual_subscription-18.0.1.0.0.3.dist-info/WHEEL
odoo_addon_account_cutoff_accrual_subscription-18.0.1.0.0.3.dist-info/top_level.txt
odoo_addon_account_cutoff_accrual_subscription-18.0.1.0.0.3.dist-info/RECORD
